{
  "id": "bvlgari-resort-bali",
  "name_zh": "峇里島寶格麗度假村",
  "name_en_official": "Bvlgari Resort Bali",
  "brand_or_group": "Bvlgari Hotels & Resorts",
  "venue_operator_type": "resort",
  "is_standalone": false,
  "region": "Uluwatu",
  "subarea": "Pecatu",
  "official_website": "https://www.bulgarihotels.com/en_US/bali",
  "maps_url": "https://www.google.com/maps/search/?api=1&query=Bvlgari+Resort+Bali",
  "address_text": "Jalan Goa Lempeh, Banjar Dinas Kangin, Uluwatu, Bali 80364, Indonesia",
  "venue_types": [
    "cliffside",
    "chapel",
    "villa-buyout",
    "water-platform"
  ],
  "primary_visual_identity": "超豪華懸崖度假村，擁有寶格麗教堂、私人別墅和俯瞰印度洋的豪宅泳池儀式。",
  "ceremony_space_types": [
    "chapel",
    "villa-pool-stage",
    "mansion-pool-stage",
    "clifftop-terrace"
  ],
  "reception_space_types": [
    "villa-dining",
    "mansion-dining",
    "terrace",
    "restaurant-room"
  ],
  "supports_ceremony_only": true,
  "supports_ceremony_and_dinner": true,
  "supports_buyout": true,
  "supports_micro_wedding": true,
  "guest_capacity_ceremony_min": 10,
  "guest_capacity_ceremony_max": 90,
  "guest_capacity_dinner_min": 10,
  "guest_capacity_dinner_max": 100,
  "recommended_guest_size_band": "51-80",
  "pricing_status": "public_price_available",
  "price_entries": [
    {
      "label": "30 位賓客的基本婚禮套餐",
      "currency": "USD",
      "amount_min": 23200,
      "amount_max": null,
      "pricing_year": 2026,
      "includes_stay": false,
      "includes_decoration": true,
      "includes_dinner": false,
      "includes_tax_service": false,
      "conditions_text": "目前 30 位客人的第三方即時報價基準；直接與寶格麗確認確切的稅金和包含範圍。",
      "confidence": "medium"
    },
    {
      "label": "寶格麗別墅婚禮",
      "currency": "IDR",
      "amount_min": 398000000,
      "amount_max": null,
      "pricing_year": 2024,
      "includes_stay": true,
      "includes_decoration": true,
      "includes_dinner": true,
      "includes_tax_service": true,
      "conditions_text": "2024年3月公開Bvlgari Villa專案頁面；包括兩晚別墅住宿、機場接送和最多 10 人的私人晚宴，需額外支付參加費用和不適用日期。",
      "confidence": "high"
    },
    {
      "label": "寶格麗豪宅婚禮",
      "currency": "IDR",
      "amount_min": 508000000,
      "amount_max": null,
      "pricing_year": 2024,
      "includes_stay": true,
      "includes_decoration": true,
      "includes_dinner": true,
      "includes_tax_service": true,
      "conditions_text": "2024 年 3 月公開 Mansion 專案頁面；包括兩晚五臥室豪宅住宿、機場接送和最多 10 人的私人晚宴，需額外支付出席費用和不適用日期。",
      "confidence": "high"
    },
    {
      "label": "草坪婚禮小型套餐",
      "currency": "CNY",
      "amount_min": 83800,
      "amount_max": null,
      "pricing_year": 2026,
      "includes_stay": true,
      "includes_decoration": true,
      "includes_dinner": true,
      "includes_tax_service": false,
      "conditions_text": "頂級奢華環境、海天一線景觀，適合親密小型婚禮",
      "source_id": "xhs-folder-12",
      "confidence": "medium"
    },
    {
      "label": "WeddingKu・La Terrazza（Garden Wedding，60人起）",
      "currency": "IDR",
      "amount_min": 130680000,
      "amount_max": null,
      "pricing_year": 2026,
      "includes_stay": false,
      "includes_decoration": false,
      "includes_dinner": true,
      "includes_tax_service": false,
      "conditions_text": "WeddingKu 標示 IDR 2,178,000/人，最少 60 人，餐飲費用基準；不含儀式費、佈置、住宿及稅服費。",
      "source_id": "bvlgari-resort-bali-weddingku-vendor",
      "confidence": "medium"
    },
    {
      "label": "WeddingKu・The Bvlgari Mansion（Private Villa，50人起）",
      "currency": "IDR",
      "amount_min": 108900000,
      "amount_max": null,
      "pricing_year": 2026,
      "includes_stay": false,
      "includes_decoration": false,
      "includes_dinner": true,
      "includes_tax_service": false,
      "conditions_text": "WeddingKu 標示 IDR 2,178,000/人，最少 50 人，餐飲費用基準；不含儀式費、佈置、住宿及稅服費。",
      "source_id": "bvlgari-resort-bali-weddingku-vendor",
      "confidence": "medium"
    },
    {
      "label": "WeddingKu・The Bvlgari Villa（Private Villa，50人起）",
      "currency": "IDR",
      "amount_min": 108900000,
      "amount_max": null,
      "pricing_year": 2026,
      "includes_stay": false,
      "includes_decoration": false,
      "includes_dinner": true,
      "includes_tax_service": false,
      "conditions_text": "WeddingKu 標示 IDR 2,178,000/人，最少 50 人，餐飲費用基準；不含儀式費、佈置、住宿及稅服費。",
      "source_id": "bvlgari-resort-bali-weddingku-vendor",
      "confidence": "medium"
    }
  ],
  "price_summary_text": "Bvlgari 是第一批中公開門檻最高的企業之一：目前的即時報價頁面起價約為 23,200 美元（可供 30 名賓客使用），而公開的 2024 年 Bvlgari Villa 和 Mansion 頁面仍分別顯示淨價 398,000,000 印尼盾和 500,000,000 印尼盾。",
  "price_risk_level": "low",
  "rain_backup_status": "strong",
  "has_indoor_backup": true,
  "has_covered_backup": true,
  "backup_space_description": "寶格麗教堂是一個室內儀式空間，室內餐廳、露臺和別墅內部接待處可以支援對天氣敏感的室外形式。",
  "backup_quality_notes": "對於親密的豪華婚禮來說，防雨能力很強，因為度假村可以將教堂、室內房間和私人別墅內部結合起來，而不會失去品牌契合度。",
  "weather_exposure_notes": "儘管度假村提供強大的室內替代方案，但別墅、豪宅和露台形式仍然暴露在懸崖頂的風和天氣之下。",
  "airport_drive_time_minutes_estimate": 45,
  "transport_notes": "寶格麗官方頁面公佈了機場計程車和飯店接送服務的價格，而目前的旅遊資訊來源通常認為度假村距離機場約 45 分鐘路程，具體取決於烏魯瓦圖的交通情況。",
  "traffic_risk_level": "high",
  "onsite_accommodation_available": true,
  "onsite_room_inventory_notes": "寶格麗正式確認了59座專屬別墅和豪宅，使入住體驗成為婚禮主張的重要組成部分。",
  "nearby_accommodation_notes": "主要婚禮派對通常可以在現場舉行，但較大的教堂客人數量可能仍需要烏魯瓦圖或培卡圖周圍有接駁車的飯店。",
  "accommodation_fit": "one_stop",
  "guest_mobility_notes": "懸崖頂的佈局和別墅分佈的移動使得嬰兒車的協調對於老年客人來說非常重要，特別是在使用多個婚禮空間時。",
  "restriction_level": "high",
  "noise_cutoff_notes": "確認各場地目前的接待和餘興活動截止時間；與大型度假村宴會廳相比，寶格麗的奢華形式不太適合深夜喧鬧的派對。",
  "external_vendor_policy": "寶格麗是嚴格控制的豪華度假村，因此在接受外部團隊之前，請先確認外部策劃者、花店、樂隊、製作和攝影許可。",
  "minimum_stay_requirement_notes": "寶格麗 (Bvlgari) 公共婚禮頁面顯示了兩晚住宿要求，對於某些形式，還要求有五個別墅單位或更多。",
  "minimum_spend_notes": "額外的與會者費用和住宿承諾是公開的，但全套食品、飲料和最低製作量應根據所選場地形式進行確認。",
  "drone_policy_notes": "儘早確認無人機的書面批准，因為對隱私敏感的別墅和懸崖邊緣的儀式區可能受到嚴格監管。",
  "family_child_notes": "最適合成人奢侈品群體；孩子們可以參加，但度假村的基調和懸崖頂的豪華佈局不像以家庭為中心的綜合度假村那麼隨意。",
  "religious_or_space_use_notes": "除非單獨安排，否則教堂通常具有像徵意義，有些夫婦可能更喜歡別墅或豪宅的形式，以進行更私人的世俗慶祝活動。",
  "operational_constraints_notes": "節日限制日期和別墅之夜的承諾是公開可見的，因此大型婚禮應該期待更高的協調和固定成本承諾。",
  "style_tags": [
    "ultra-luxury",
    "cliffside",
    "italian-balinese",
    "chapel",
    "villa-buyout",
    "private-pool"
  ],
  "price_band_normalized": null,
  "best_for": [
    "情侶優先考慮超豪華隱私和品牌服務",
    "想要選擇有教堂的別墅住宿的中小型客人",
    "慶祝活動，住宿本身就是奢華宣言的一部分"
  ],
  "not_ideal_for": [
    "價值驅動的目的地婚禮",
    "非常休閒的家庭團體，尋找輕鬆的平坦運動",
    "在詢價前需要廣泛公開價格透明度的夫婦"
  ],
  "key_strengths": [
    "以別墅為基礎的住宿，具有強烈的豪華定位",
    "明確教堂、別墅和豪宅格式的公共容量錨點",
    "透過教堂和室內替代方案，為親密婚禮提供強大的雨水靈活性",
    "（小紅書用戶實測）服務高度客製化，能根據新人性格（年輕、時尚、愛花藝）量身打造",
    "（小紅書用戶實測）可承辦小型精緻婚禮（58人）且兼具奢華感",
    "WeddingKu 評分 4.8/5.0（2 則評論）（WeddingKu 平台資料）"
  ],
  "key_risks": [
    "非常高的入門價格和別墅之夜承諾",
    "節日限制日期和每人附加費",
    "烏魯瓦圖交通和懸崖頂運動仍需規劃"
  ],
  "wedding_spaces": [
    {
      "space_id": "bvlgari-chapel",
      "label": "寶格麗教堂",
      "space_types": [
        "chapel"
      ],
      "privacy_level": "shared",
      "event_scope": "ceremony_only",
      "capacity_summary_text": "公開資料多指向象徵儀式最多約 90 人，是寶格麗最穩定的室內儀式主場。",
      "price_summary_text": "若你把雨備穩定、教堂感與長輩接受度放在第一順位，教堂通常是最容易 shortlist 的公開形式；晚宴仍要再接其他空間。",
      "backup_summary_text": "本身就是室內儀式空間，遇雨幾乎不需要改變婚禮主邏輯。",
      "decision_notes": "適合重視品牌教堂感、天候穩定性與儀式感的人，缺點是私密度與住宿一體化不如別墅 / 豪宅玩法。"
    },
    {
      "space_id": "public-water-wedding-stage",
      "label": "公開水中婚禮台",
      "space_types": [
        "water-platform"
      ],
      "privacy_level": "shared",
      "event_scope": "ceremony_only",
      "capacity_summary_text": "透明祭壇設在面海水景前方，重點是拿到寶格麗最經典的水上儀式畫面；常見做法是儀式後再接別處晚宴。",
      "price_summary_text": "通常比私人別墅 / 豪宅買斷型更容易切入，但公開價格與最新可接人數仍需逐案確認。",
      "backup_summary_text": "遇雨多半要回到教堂或其他室內區域，私密度與改場自由度都不如買斷型水台。",
      "decision_notes": "如果你要的是寶格麗經典的面海透明祭壇視覺，但不一定想綁整棟別墅，這是最該先問的公開型玩法。"
    },
    {
      "space_id": "la-terrazza",
      "label": "La Terrazza 海景露台",
      "space_types": [
        "cliffside"
      ],
      "privacy_level": "semi-private",
      "event_scope": "ceremony_and_dinner",
      "capacity_summary_text": "公開案例常見到 12 人級距，保留海景與餐廳氣氛，但不是別墅／豪宅那種完整私有場地。",
      "price_summary_text": "屬較輕量的海景露台玩法，通常比別墅 / 豪宅包場更容易談，但仍要逐案確認最低消費與晚宴形式。",
      "backup_summary_text": "遇雨多半要轉向室內餐飲空間或教堂備案，空間彈性不如買斷式形式。",
      "decision_notes": "適合只想要少人數、海景與精緻晚餐氛圍，不追求最高私密性與最強浮台識別度的組合。"
    },
    {
      "space_id": "bvlgari-villa-private-water-stage",
      "label": "Bvlgari Villa 私人水台",
      "space_types": [
        "water-platform",
        "villa-buyout"
      ],
      "privacy_level": "private",
      "event_scope": "buyout_event",
      "capacity_summary_text": "公開資料多指向最多約 50 人；樓下酒會露台加樓上映池水台，是最典型的私人別墅婚禮格式。",
      "price_summary_text": "2024 年公開專案起價約 IDR 398,000,000，並綁兩晚別墅住宿、私人晚宴與接送條件。",
      "backup_summary_text": "雨天可轉為別墅室內、教堂或其他室內區域，但流程與空間切換都需要飯店高度協調。",
      "decision_notes": "比公開水台更私密，也更能把住宿體驗綁進婚禮主軸；代價是住宿承諾與總預算門檻明顯拉高。"
    },
    {
      "space_id": "bvlgari-mansion-private-water-stage",
      "label": "Bvlgari Mansion 總裁豪宅私人水台",
      "space_types": [
        "water-platform",
        "villa-buyout"
      ],
      "privacy_level": "private",
      "event_scope": "buyout_event",
      "capacity_summary_text": "公開資料多指向最多約 50 人；五房豪宅加 T 字型透明水台，是寶格麗最具總裁級私密感的版本。",
      "price_summary_text": "2024 年公開專案起價約 IDR 508,000,000，通常是寶格麗最昂貴、也最完整的豪宅買斷玩法。",
      "backup_summary_text": "遇雨可轉豪宅室內、教堂或其他室內區域，但整體仍高度依賴現場協調與時段管理。",
      "decision_notes": "如果你在意總裁級私密性、浮台儀式與住宿儀式一體化，這是最接近寶格麗終極版本的選擇。"
    }
  ],
  "data_completeness": "comparable_core_complete",
  "research_status": "deep_research_complete",
  "last_verified_at": "2026-06-18",
  "data_freshness": "recent",
  "open_questions": [
    "確認目前哪些形式支援 50 位以上賓客的全座接待晚宴，而無需離開標誌性場地。",
    "確認最新的外部供應商審批規則和製作費用。",
    "確認當前的聲音截止和最佳的酒店內派對替代方案。"
  ],
  "source_ids": [
    "bvlgari-balifortwo-jeffrey-mag",
    "bvlgari-balifortwo-la-terrazza",
    "bvlgari-balifortwo-villa",
    "bvlgari-balivibes-overview",
    "bvlgari-bridestory-chapel",
    "bvlgari-bridestory-mansion",
    "bvlgari-bridestory-villa",
    "bvlgari-ctrip-hotel",
    "bvlgari-myoverseaswedding",
    "bvlgari-neverneverland-zh",
    "bvlgari-official-chapel",
    "bvlgari-official-location",
    "bvlgari-official-mansion",
    "bvlgari-official-ocean-view-villa",
    "bvlgari-official-overview",
    "bvlgari-official-villa",
    "bvlgari-resort-bali-suka-zh",
    "bvlgari-resort-bali-sweetday-resort-zh",
    "bvlgari-resort-bali-sweetday-water-zh",
    "bvlgari-resort-bali-watabe-ja",
    "bvlgari-resort-bali-weddings-com-tw-portfolio-zh",
    "bvlgari-resort-bali-xhs-post-4",
    "bvlgari-resort-bali-xhs-post-6",
    "bvlgari-resort-bali-xhs-post-8",
    "bvlgari-tripcom-hk-hotel",
    "bvlgari-resort-bali-xhs-post-15",
    "bvlgari-resort-bali-xhs-post-12",
    "bvlgari-resort-bali-xhs-post-19",
    "bvlgari-resort-bali-weddingku-vendor",
    "bvlgari-theweddingnotebook-silent-songs",
    "bvlgari-balifortwo-tony-beixi",
    "bvlgari-balifortwo-daniel-gisela",
    "bvlgari-balifortwo-apoorva-nahin",
    "bvlgari-balifortwo-emmanuel-jocelyn",
    "bvlgari-balifortwo-ze-dany",
    "bvlgari-balifortwo-julian-joan",
    "bvlgari-balifortwo-erika-stephen",
    "bvlgari-balifortwo-vanessa-daniel",
    "bvlgari-balifortwo-mandy-michael",
    "bvlgari-balifortwo-gaby-colton",
    "bvlgari-balifortwo-dyan-daniel"
  ],
  "photo_index_id": "bvlgari-resort-bali",
  "last_updated": "2026-06-21T16:53:06.908352"
}