[
  {
    "photo_entry_id": "six-senses-uluwatu-bali-photo-official-weddings",
    "venue_id": "six-senses-uluwatu-bali",
    "source_id": "six-senses-uluwatu-bali-official-weddings",
    "page_url": "https://www.sixsenses.com/en/hotels-resorts/asia-the-pacific/indonesia/uluwatu-bali/meetings/weddings/",
    "image_url_or_gallery_url": "https://www.sixsenses.com/en/hotels-resorts/asia-the-pacific/indonesia/uluwatu-bali/meetings/weddings/",
    "image_type": "official_wedding_gallery",
    "scene_tags": [
      "cliffside-ceremony",
      "floral-setup",
      "guest-seating"
    ],
    "authenticity": "official_promotional",
    "coverage_type": "large_gallery",
    "decision_value": "high",
    "decision_notes": "六善婚禮視覺效果和場地組合的最佳官方切入點。"
  },
  {
    "photo_entry_id": "six-senses-uluwatu-bali-photo-official-meetings",
    "venue_id": "six-senses-uluwatu-bali",
    "source_id": "six-senses-uluwatu-bali-official-meetings",
    "page_url": "https://www.sixsenses.com/en/hotels-resorts/asia-the-pacific/indonesia/uluwatu-bali/meetings/",
    "image_url_or_gallery_url": "https://www.sixsenses.com/en/hotels-resorts/asia-the-pacific/indonesia/uluwatu-bali/meetings/",
    "image_type": "official_wedding_gallery",
    "scene_tags": [
      "ballroom-reception",
      "cliffside-ceremony",
      "guest-seating"
    ],
    "authenticity": "official_promotional",
    "coverage_type": "large_gallery",
    "decision_value": "high",
    "decision_notes": "對於了解六善如何平衡引人注目的戶外空間與宴會廳後備空間非常重要。"
  },
  {
    "photo_entry_id": "six-senses-uluwatu-bali-photo-official-resort",
    "venue_id": "six-senses-uluwatu-bali",
    "source_id": "six-senses-uluwatu-bali-official-resort",
    "page_url": "https://www.sixsenses.com/en/hotels-resorts/asia-the-pacific/indonesia/uluwatu-bali/",
    "image_url_or_gallery_url": "https://www.sixsenses.com/en/hotels-resorts/asia-the-pacific/indonesia/uluwatu-bali/",
    "image_type": "official_hotel_gallery",
    "scene_tags": [
      "public-area",
      "arrival-flow",
      "jungle-view"
    ],
    "authenticity": "official_promotional",
    "coverage_type": "large_gallery",
    "decision_value": "medium",
    "decision_notes": "對於整體度假村氣氛和流通而不是婚禮佈置細節很有用。"
  },
  {
    "photo_entry_id": "six-senses-uluwatu-bali-photo-official-accommodations",
    "venue_id": "six-senses-uluwatu-bali",
    "source_id": "six-senses-uluwatu-bali-official-accommodations",
    "page_url": "https://www.sixsenses.com/en/hotels-resorts/asia-the-pacific/indonesia/uluwatu-bali/accommodation/",
    "image_url_or_gallery_url": "https://www.sixsenses.com/en/hotels-resorts/asia-the-pacific/indonesia/uluwatu-bali/accommodation/",
    "image_type": "official_hotel_gallery",
    "scene_tags": [
      "room",
      "public-area"
    ],
    "authenticity": "official_promotional",
    "coverage_type": "large_gallery",
    "decision_value": "medium",
    "decision_notes": "為賓客住宿產品是否符合婚禮的奢華期望提供良好的參考。"
  },
  {
    "photo_entry_id": "six-senses-uluwatu-bali-photo-official-cliff-bar",
    "venue_id": "six-senses-uluwatu-bali",
    "source_id": "six-senses-uluwatu-bali-official-cliff-bar",
    "page_url": "https://www.sixsenses.com/en/hotels-resorts/asia-the-pacific/indonesia/uluwatu-bali/dining/the-cliff-bar/",
    "image_url_or_gallery_url": "https://www.sixsenses.com/en/hotels-resorts/asia-the-pacific/indonesia/uluwatu-bali/dining/the-cliff-bar/",
    "image_type": "official_hotel_gallery",
    "scene_tags": [
      "night-view",
      "public-area"
    ],
    "authenticity": "official_promotional",
    "coverage_type": "small_gallery",
    "decision_value": "medium",
    "decision_notes": "對於天黑後的氛圍和更廣闊的懸崖邊氛圍很有用。"
  },
  {
    "photo_entry_id": "six-senses-uluwatu-bali-photo-myoverseas-overview",
    "venue_id": "six-senses-uluwatu-bali",
    "source_id": "six-senses-uluwatu-bali-myoverseas-overview",
    "page_url": "https://www.myoverseaswedding.com/wedding-destinations/bali/six-senses-uluwatu-bali",
    "image_url_or_gallery_url": "https://www.myoverseaswedding.com/wedding-destinations/bali/six-senses-uluwatu-bali",
    "image_type": "platform_listing_gallery",
    "scene_tags": [
      "cliffside-ceremony",
      "guest-seating",
      "night-view"
    ],
    "authenticity": "official_promotional",
    "coverage_type": "large_gallery",
    "decision_value": "high",
    "decision_notes": "強大的面向策劃者的畫廊，將主要婚禮造型集中在一個地方。"
  },
  {
    "photo_entry_id": "six-senses-uluwatu-bali-photo-myoverseas-ceremony",
    "venue_id": "six-senses-uluwatu-bali",
    "source_id": "six-senses-uluwatu-bali-myoverseas-ceremony",
    "page_url": "https://www.myoverseaswedding.com/wedding-destinations/bali/six-senses-uluwatu-bali/ceremony-venues",
    "image_url_or_gallery_url": "https://www.myoverseaswedding.com/wedding-destinations/bali/six-senses-uluwatu-bali/ceremony-venues",
    "image_type": "platform_listing_gallery",
    "scene_tags": [
      "cliffside-ceremony",
      "floral-setup",
      "guest-seating"
    ],
    "authenticity": "official_promotional",
    "coverage_type": "large_gallery",
    "decision_value": "high",
    "decision_notes": "有助於比較安達卡拉草坪、天堂電影院和靜修儀式的感覺。"
  },
  {
    "photo_entry_id": "six-senses-uluwatu-bali-photo-bridestory-venue",
    "venue_id": "six-senses-uluwatu-bali",
    "source_id": "six-senses-uluwatu-bali-bridestory-venue",
    "page_url": "https://www.bridestory.com/six-senses-uluwatu",
    "image_url_or_gallery_url": "https://www.bridestory.com/six-senses-uluwatu",
    "image_type": "platform_listing_gallery",
    "scene_tags": [
      "cliffside-ceremony",
      "ballroom-reception",
      "guest-seating"
    ],
    "authenticity": "official_promotional",
    "coverage_type": "small_gallery",
    "decision_value": "medium",
    "decision_notes": "如果您要快速比較多個場所的市場視覺效果，則這是有用的備份庫。"
  },
  {
    "photo_entry_id": "six-senses-uluwatu-bali-photo-bridestory-store",
    "venue_id": "six-senses-uluwatu-bali",
    "source_id": "six-senses-uluwatu-bali-bridestory-store",
    "page_url": "https://www.bridestory.com/six-senses-uluwatu/store",
    "image_url_or_gallery_url": "https://www.bridestory.com/six-senses-uluwatu/store",
    "image_type": "platform_listing_gallery",
    "scene_tags": [
      "cliffside-ceremony",
      "night-view",
      "public-area"
    ],
    "authenticity": "unknown",
    "coverage_type": "small_gallery",
    "decision_value": "medium",
    "decision_notes": "即使包裝的新鮮度需要重新確認，也會添加另一層婚禮特定的視覺瀏覽。"
  },
  {
    "photo_entry_id": "six-senses-uluwatu-bali-photo-official-zh-resort",
    "venue_id": "six-senses-uluwatu-bali",
    "source_id": "six-senses-uluwatu-bali-official-zh-resort",
    "page_url": "https://www.sixsenses.com/zh/hotels-resorts/asia-the-pacific/indonesia/uluwatu-bali/",
    "image_url_or_gallery_url": "https://www.sixsenses.com/zh/hotels-resorts/asia-the-pacific/indonesia/uluwatu-bali/",
    "image_type": "official_hotel_gallery",
    "scene_tags": [
      "public-area",
      "night-view",
      "room"
    ],
    "authenticity": "official_promotional",
    "coverage_type": "large_gallery",
    "decision_value": "medium",
    "decision_notes": "有用的中文官方畫廊，適用於別墅、公共區域和整體懸崖度假村氛圍。"
  },
  {
    "photo_entry_id": "six-senses-uluwatu-bali-photo-official-zh-weddings",
    "venue_id": "six-senses-uluwatu-bali",
    "source_id": "six-senses-uluwatu-bali-official-zh-weddings",
    "page_url": "https://www.sixsenses.com/zh/hotels-resorts/asia-the-pacific/indonesia/uluwatu-bali/meetings/weddings/",
    "image_url_or_gallery_url": "https://www.sixsenses.com/zh/hotels-resorts/asia-the-pacific/indonesia/uluwatu-bali/meetings/weddings/",
    "image_type": "official_wedding_gallery",
    "scene_tags": [
      "cliffside-ceremony",
      "ballroom-reception",
      "guest-seating"
    ],
    "authenticity": "official_promotional",
    "coverage_type": "large_gallery",
    "decision_value": "high",
    "decision_notes": "比較六善戶外場地與宴會廳備援的最佳中文官方頁面。"
  },
  {
    "photo_entry_id": "six-senses-uluwatu-bali-photo-ctrip",
    "venue_id": "six-senses-uluwatu-bali",
    "source_id": "six-senses-uluwatu-bali-ctrip-hotel",
    "page_url": "https://hotels.ctrip.com/hotels/21888559.html",
    "image_url_or_gallery_url": "https://hotels.ctrip.com/hotels/21888559.html",
    "image_type": "platform_listing_gallery",
    "scene_tags": [
      "room",
      "public-area",
      "night-view"
    ],
    "authenticity": "unknown",
    "coverage_type": "large_gallery",
    "decision_value": "medium",
    "decision_notes": "有用的中文飯店畫廊，包括客房、游泳池和懸崖邊的公共區域。"
  },
  {
    "photo_entry_id": "six-senses-uluwatu-bali-photo-licheng",
    "venue_id": "six-senses-uluwatu-bali",
    "source_id": "six-senses-uluwatu-bali-licheng-chinese-venue",
    "page_url": "https://www.lichenglove.com/hotel/bali-hotel-1953",
    "image_url_or_gallery_url": "https://www.lichenglove.com/hotel/bali-hotel-1953",
    "image_type": "blog_feature",
    "scene_tags": [
      "cliffside-ceremony",
      "ballroom-reception",
      "guest-seating"
    ],
    "authenticity": "unknown",
    "coverage_type": "large_gallery",
    "decision_value": "high",
    "decision_notes": "中文婚禮專題，包含全景視圖和場地影像，可用於候選名單比較。"
  },
  {
    "photo_entry_id": "six-senses-uluwatu-bali-balifortwo-aarunya-50",
    "venue_id": "six-senses-uluwatu-bali",
    "source_id": "six-senses-uluwatu-bali-balifortwo-aarunya-50",
    "page_url": "https://balifortwo2.com/six-senses-uluwatu-enchanting-aarunya-50-pax/",
    "image_url_or_gallery_url": "https://balifortwo2.com/six-senses-uluwatu-enchanting-aarunya-50-pax/",
    "image_type": "platform_listing_gallery",
    "scene_tags": [
      "cliffside-ceremony",
      "guest-seating",
      "night-view"
    ],
    "authenticity": "unknown",
    "coverage_type": "large_gallery",
    "decision_value": "high",
    "decision_notes": "可直接看 Six Senses Aarunya 50 人規模的儀式與晚宴配置。"
  },
  {
    "photo_entry_id": "six-senses-uluwatu-bali-neverneverland-zh",
    "venue_id": "six-senses-uluwatu-bali",
    "source_id": "six-senses-uluwatu-bali-neverneverland-zh",
    "page_url": "https://neverneverlandinbali.com/wedding/17033-2/",
    "image_url_or_gallery_url": "https://neverneverlandinbali.com/wedding/17033-2/",
    "image_type": "blog_feature",
    "scene_tags": [
      "cliffside-ceremony",
      "ballroom-reception",
      "public-area",
      "night-view"
    ],
    "authenticity": "unknown",
    "coverage_type": "large_gallery",
    "decision_value": "high",
    "decision_notes": "中文頁圖片多，能快速補足 Six Senses 儀式、宴會與公共空間的實際感。"
  }
]
